flask_leancloud_sms.py
setup.py
Flask_Leancloud_Sms.egg-info/PKG-INFO
Flask_Leancloud_Sms.egg-info/SOURCES.txt
Flask_Leancloud_Sms.egg-info/dependency_links.txt
Flask_Leancloud_Sms.egg-info/not-zip-safe
Flask_Leancloud_Sms.egg-info/requires.txt
Flask_Leancloud_Sms.egg-info/top_level.txt