Metadata-Version: 1.1
Name: Flask-Leancloud-Sms
Version: 0.1
Summary: Leancloud SMS Service for Flask
Home-page: http://github.com/n0trace/flask-leancloud-sms/
Author: n0trace
Author-email: n0trace@protonmail.com
License: MIT
Platform: any
Classifier: Environment :: Web Environment
Classifier: Intended Audience :: Developers
Classifier: License :: OSI Approved :: MIT License
Classifier: Operating System :: OS Independent
Classifier: Programming Language :: Python
Classifier: Topic :: Internet :: WWW/HTTP :: Dynamic Content
Classifier: Topic :: Software Development :: Libraries :: Python Modules
